odoo8_addon_l10n_id_taxform-8.0.1.0.0-py2.7-nspkg.pth
odoo_addons/l10n_id_taxform/__openerp__.py
odoo_addons/l10n_id_taxform/menu.xml
odoo_addons/l10n_id_taxform/__init__.py
odoo_addons/l10n_id_taxform/README.rst
odoo_addons/l10n_id_taxform/security/taxform_groups.xml
odoo_addons/l10n_id_taxform/static/description/icon.png
odoo8_addon_l10n_id_taxform-8.0.1.0.0.dist-info/top_level.txt
odoo8_addon_l10n_id_taxform-8.0.1.0.0.dist-info/WHEEL
odoo8_addon_l10n_id_taxform-8.0.1.0.0.dist-info/RECORD
odoo8_addon_l10n_id_taxform-8.0.1.0.0.dist-info/metadata.json
odoo8_addon_l10n_id_taxform-8.0.1.0.0.dist-info/DESCRIPTION.rst
odoo8_addon_l10n_id_taxform-8.0.1.0.0.dist-info/METADATA
odoo8_addon_l10n_id_taxform-8.0.1.0.0.dist-info/namespace_packages.txt
